streamx/__init__.py
streamx/stream.py
tests/__init__.py
tests/test_stream.py
streamx-0.0.5.dist-info/LICENSE
streamx-0.0.5.dist-info/METADATA
streamx-0.0.5.dist-info/WHEEL
streamx-0.0.5.dist-info/top_level.txt
streamx-0.0.5.dist-info/RECORD
