Metadata-Version: 2.1
Name: streamx
Version: 0.0.5
Summary: The simple solution for sharing async data streams in Python.
Home-page: https://github.com/MasonFlint44/streamx
Author: Mason Flint
Author-email: masonflint44@gmail.com
Project-URL: Bug Tracker, https://github.com/MasonFlint44/streamx/issues
Classifier: Programming Language :: Python :: 3
Classifier: License :: OSI Approved :: MIT License
Classifier: Operating System :: OS Independent
Classifier: Development Status :: 3 - Alpha
Classifier: Intended Audience :: Developers
Requires-Python: >=3.7
License-File: LICENSE
